privy_python_sdk/.gitignore
privy_python_sdk/__init__.py
privy_python_sdk/privy.py
privy_python_sdk-1.0.8.dist-info/METADATA
privy_python_sdk-1.0.8.dist-info/WHEEL
privy_python_sdk-1.0.8.dist-info/RECORD
