Metadata-Version: 2.1
Name: privy-python-sdk
Version: 1.0.8
Summary: Python SDK for Privy Digital Signature
Home-page: https://github.com/landx-id/privy-python-sdk
License: MIT
Keywords: privy,digital Signature,LandX
Author: LandX Engineering
Author-email: tech@landx.id
Requires-Python: >=3.9,<4.0
Classifier: License :: OSI Approved :: MIT License
Classifier: Programming Language :: Python :: 3
Classifier: Programming Language :: Python :: 3.9
Classifier: Programming Language :: Python :: 3.10
Classifier: Programming Language :: Python :: 3.11
Project-URL: Repository, https://github.com/landx-id/privy-python-sdk
